public final class FOO implements run/endive/runtime/Machine {

  private final Lrun/endive/runtime/Instance; instance

  private final Lrun/endive/runtime/internal/CompilerInterpreterMachine; compilerInterpreterMachine

  public <init>(Lrun/endive/runtime/Instance;)V
    ALOAD 0
    INVOKESPECIAL java/lang/Object.<init> ()V
    ALOAD 0
    ALOAD 1
    PUTFIELD FOO.instance : Lrun/endive/runtime/Instance;
    RETURN

  public call(I[J)[J
    TRYCATCHBLOCK L0 L1 L1 java/lang/StackOverflowError
    ACONST_NULL
    ASTORE 3
   L0
    ALOAD 0
    GETFIELD FOO.instance : Lrun/endive/runtime/Instance;
    DUP
    INVOKEVIRTUAL run/endive/runtime/Instance.memory ()Lrun/endive/runtime/Memory;
    ILOAD 1
    ALOAD 2
    ALOAD 3
    INVOKESTATIC FOOMachineCall.call (Lrun/endive/runtime/Instance;Lrun/endive/runtime/Memory;I[J[Ljava/lang/Object;)[J
    ARETURN
   L1
    INVOKESTATIC FOOShaded.throwCallStackExhausted (Ljava/lang/StackOverflowError;)Ljava/lang/RuntimeException;
    ATHROW

  public call(I[J[Ljava/lang/Object;)[J
    TRYCATCHBLOCK L0 L1 L1 java/lang/StackOverflowError
   L0
    ALOAD 0
    GETFIELD FOO.instance : Lrun/endive/runtime/Instance;
    DUP
    INVOKEVIRTUAL run/endive/runtime/Instance.memory ()Lrun/endive/runtime/Memory;
    ILOAD 1
    ALOAD 2
    ALOAD 3
    INVOKESTATIC FOOMachineCall.call (Lrun/endive/runtime/Instance;Lrun/endive/runtime/Memory;I[J[Ljava/lang/Object;)[J
    ARETURN
   L1
    INVOKESTATIC FOOShaded.throwCallStackExhausted (Ljava/lang/StackOverflowError;)Ljava/lang/RuntimeException;
    ATHROW

  public callWithRefs(I[J[Ljava/lang/Object;)Lrun/endive/runtime/CallResult;
    ALOAD 0
    ILOAD 1
    ALOAD 2
    ALOAD 3
    INVOKEVIRTUAL FOO.call (I[J[Ljava/lang/Object;)[J
    ACONST_NULL
    INVOKESTATIC run/endive/runtime/CallResult.of ([J[Ljava/lang/Object;)Lrun/endive/runtime/CallResult;
    ARETURN

  public static call_indirect_0(IILrun/endive/runtime/Memory;Lrun/endive/runtime/Instance;)V
    INVOKESTATIC FOOShaded.checkInterruption ()V
    ALOAD 3
    ILOAD 1
    INVOKEVIRTUAL run/endive/runtime/Instance.table (I)Lrun/endive/runtime/TableInstance;
    ASTORE 4
    ALOAD 4
    ILOAD 0
    INVOKEVIRTUAL run/endive/runtime/TableInstance.requiredRef (I)I
    ISTORE 5
    ALOAD 4
    ILOAD 0
    INVOKEVIRTUAL run/endive/runtime/TableInstance.instance (I)Lrun/endive/runtime/Instance;
    ASTORE 6
    ALOAD 6
    IFNULL L0
    ALOAD 6
    ALOAD 3
    IF_ACMPNE L1
   L0
    ALOAD 2
    ALOAD 3
    ILOAD 5
    LOOKUPSWITCH
      0: L2
      default: L3
   L2
    INVOKESTATIC FOOFuncGroup_0.func_0 (Lrun/endive/runtime/Memory;Lrun/endive/runtime/Instance;)V
    RETURN
   L3
    INVOKESTATIC FOOShaded.throwIndirectCallTypeMismatch ()Ljava/lang/RuntimeException;
    ATHROW
   L1
    ICONST_0
    NEWARRAY T_LONG
    ICONST_0
    ILOAD 5
    ALOAD 6
    INVOKESTATIC FOOShaded.callIndirect ([JIILrun/endive/runtime/Instance;)[J
    RETURN
}
