public final class run/endive/$gen/CompiledMachine implements run/endive/runtime/Machine {

  private final Lrun/endive/runtime/Instance; instance

  private final Lrun/endive/runtime/internal/CompilerInterpreterMachine; compilerInterpreterMachine

  public <init>(Lrun/endive/runtime/Instance;)V
    ALOAD 0
    INVOKESPECIAL java/lang/Object.<init> ()V
    ALOAD 0
    ALOAD 1
    PUTFIELD run/endive/$gen/CompiledMachine.instance : Lrun/endive/runtime/Instance;
    ALOAD 0
    NEW run/endive/runtime/internal/CompilerInterpreterMachine
    DUP
    ALOAD 1
    ICONST_0
    NEWARRAY T_INT
    INVOKESPECIAL run/endive/runtime/internal/CompilerInterpreterMachine.<init> (Lrun/endive/runtime/Instance;[I)V
    PUTFIELD run/endive/$gen/CompiledMachine.compilerInterpreterMachine : Lrun/endive/runtime/internal/CompilerInterpreterMachine;
    RETURN

  public call(I[J)[J
    TRYCATCHBLOCK L0 L1 L1 java/lang/StackOverflowError
    ACONST_NULL
    ASTORE 3
   L0
    ALOAD 0
    GETFIELD run/endive/$gen/CompiledMachine.instance : Lrun/endive/runtime/Instance;
    DUP
    INVOKEVIRTUAL run/endive/runtime/Instance.memory ()Lrun/endive/runtime/Memory;
    ILOAD 1
    ALOAD 2
    ALOAD 3
    INVOKESTATIC run/endive/$gen/CompiledMachineMachineCall.call (Lrun/endive/runtime/Instance;Lrun/endive/runtime/Memory;I[J[Ljava/lang/Object;)[J
    ARETURN
   L1
    INVOKESTATIC run/endive/$gen/CompiledMachineShaded.throwCallStackExhausted (Ljava/lang/StackOverflowError;)Ljava/lang/RuntimeException;
    ATHROW

  public call(I[J[Ljava/lang/Object;)[J
    TRYCATCHBLOCK L0 L1 L1 java/lang/StackOverflowError
   L0
    ALOAD 0
    GETFIELD run/endive/$gen/CompiledMachine.instance : Lrun/endive/runtime/Instance;
    DUP
    INVOKEVIRTUAL run/endive/runtime/Instance.memory ()Lrun/endive/runtime/Memory;
    ILOAD 1
    ALOAD 2
    ALOAD 3
    INVOKESTATIC run/endive/$gen/CompiledMachineMachineCall.call (Lrun/endive/runtime/Instance;Lrun/endive/runtime/Memory;I[J[Ljava/lang/Object;)[J
    ARETURN
   L1
    INVOKESTATIC run/endive/$gen/CompiledMachineShaded.throwCallStackExhausted (Ljava/lang/StackOverflowError;)Ljava/lang/RuntimeException;
    ATHROW

  public static call_indirect_0(IIILrun/endive/runtime/Memory;Lrun/endive/runtime/Instance;)I
    INVOKESTATIC run/endive/$gen/CompiledMachineShaded.checkInterruption ()V
    ALOAD 4
    ILOAD 2
    INVOKEVIRTUAL run/endive/runtime/Instance.table (I)Lrun/endive/runtime/TableInstance;
    ASTORE 5
    ALOAD 5
    ILOAD 1
    INVOKEVIRTUAL run/endive/runtime/TableInstance.requiredRef (I)I
    ISTORE 6
    ALOAD 5
    ILOAD 1
    INVOKEVIRTUAL run/endive/runtime/TableInstance.instance (I)Lrun/endive/runtime/Instance;
    ASTORE 7
    ALOAD 7
    IFNULL L0
    ALOAD 7
    ALOAD 4
    IF_ACMPNE L1
   L0
    ILOAD 0
    ALOAD 3
    ALOAD 4
    ILOAD 6
    LOOKUPSWITCH
      0: L2
      1: L3
      2: L4
      3: L5
      4: L6
      5: L7
      6: L8
      7: L9
      8: L10
      9: L11
      default: L12
   L2
    INVOKESTATIC run/endive/$gen/CompiledMachineFuncGroup_0.func_0 (ILrun/endive/runtime/Memory;Lrun/endive/runtime/Instance;)I
    IRETURN
   L3
    INVOKESTATIC run/endive/$gen/CompiledMachineFuncGroup_0.func_1 (ILrun/endive/runtime/Memory;Lrun/endive/runtime/Instance;)I
    IRETURN
   L4
    INVOKESTATIC run/endive/$gen/CompiledMachineFuncGroup_0.func_2 (ILrun/endive/runtime/Memory;Lrun/endive/runtime/Instance;)I
    IRETURN
   L5
    INVOKESTATIC run/endive/$gen/CompiledMachineFuncGroup_0.func_3 (ILrun/endive/runtime/Memory;Lrun/endive/runtime/Instance;)I
    IRETURN
   L6
    INVOKESTATIC run/endive/$gen/CompiledMachineFuncGroup_0.func_4 (ILrun/endive/runtime/Memory;Lrun/endive/runtime/Instance;)I
    IRETURN
   L7
    INVOKESTATIC run/endive/$gen/CompiledMachineFuncGroup_1.func_5 (ILrun/endive/runtime/Memory;Lrun/endive/runtime/Instance;)I
    IRETURN
   L8
    INVOKESTATIC run/endive/$gen/CompiledMachineFuncGroup_1.func_6 (ILrun/endive/runtime/Memory;Lrun/endive/runtime/Instance;)I
    IRETURN
   L9
    INVOKESTATIC run/endive/$gen/CompiledMachineFuncGroup_1.func_7 (ILrun/endive/runtime/Memory;Lrun/endive/runtime/Instance;)I
    IRETURN
   L10
    INVOKESTATIC run/endive/$gen/CompiledMachineFuncGroup_1.func_8 (ILrun/endive/runtime/Memory;Lrun/endive/runtime/Instance;)I
    IRETURN
   L11
    INVOKESTATIC run/endive/$gen/CompiledMachineFuncGroup_1.func_9 (ILrun/endive/runtime/Memory;Lrun/endive/runtime/Instance;)I
    IRETURN
   L12
    INVOKESTATIC run/endive/$gen/CompiledMachineShaded.throwIndirectCallTypeMismatch ()Ljava/lang/RuntimeException;
    ATHROW
   L1
    ICONST_1
    NEWARRAY T_LONG
    DUP
    ICONST_0
    ILOAD 0
    I2L
    LASTORE
    ICONST_0
    ILOAD 6
    ALOAD 7
    INVOKESTATIC run/endive/$gen/CompiledMachineShaded.callIndirect ([JIILrun/endive/runtime/Instance;)[J
    ICONST_0
    LALOAD
    L2I
    IRETURN
}

final class run/endive/$gen/CompiledMachineFuncGroup_0 {

  public static func_0(ILrun/endive/runtime/Memory;Lrun/endive/runtime/Instance;)I
    ILOAD 0
    ICONST_1
    IADD
    IRETURN

  public static call_0(Lrun/endive/runtime/Instance;Lrun/endive/runtime/Memory;[J[Ljava/lang/Object;)[J
    ALOAD 2
    ICONST_0
    LALOAD
    L2I
    ALOAD 1
    ALOAD 0
    INVOKESTATIC run/endive/$gen/CompiledMachineFuncGroup_0.func_0 (ILrun/endive/runtime/Memory;Lrun/endive/runtime/Instance;)I
    I2L
    LSTORE 4
    ICONST_1
    NEWARRAY T_LONG
    DUP
    ICONST_0
    LLOAD 4
    LASTORE
    ARETURN

  public static func_1(ILrun/endive/runtime/Memory;Lrun/endive/runtime/Instance;)I
    ILOAD 0
    ICONST_2
    IADD
    INVOKESTATIC run/endive/$gen/CompiledMachineShaded.checkInterruption ()V
    ALOAD 1
    ALOAD 2
    INVOKESTATIC run/endive/$gen/CompiledMachineFuncGroup_0.func_0 (ILrun/endive/runtime/Memory;Lrun/endive/runtime/Instance;)I
    IRETURN

  public static call_1(Lrun/endive/runtime/Instance;Lrun/endive/runtime/Memory;[J[Ljava/lang/Object;)[J
    ALOAD 2
    ICONST_0
    LALOAD
    L2I
    ALOAD 1
    ALOAD 0
    INVOKESTATIC run/endive/$gen/CompiledMachineFuncGroup_0.func_1 (ILrun/endive/runtime/Memory;Lrun/endive/runtime/Instance;)I
    I2L
    LSTORE 4
    ICONST_1
    NEWARRAY T_LONG
    DUP
    ICONST_0
    LLOAD 4
    LASTORE
    ARETURN

  public static func_2(ILrun/endive/runtime/Memory;Lrun/endive/runtime/Instance;)I
    ILOAD 0
    ICONST_3
    IADD
    INVOKESTATIC run/endive/$gen/CompiledMachineShaded.checkInterruption ()V
    ALOAD 1
    ALOAD 2
    INVOKESTATIC run/endive/$gen/CompiledMachineFuncGroup_0.func_1 (ILrun/endive/runtime/Memory;Lrun/endive/runtime/Instance;)I
    IRETURN

  public static call_2(Lrun/endive/runtime/Instance;Lrun/endive/runtime/Memory;[J[Ljava/lang/Object;)[J
    ALOAD 2
    ICONST_0
    LALOAD
    L2I
    ALOAD 1
    ALOAD 0
    INVOKESTATIC run/endive/$gen/CompiledMachineFuncGroup_0.func_2 (ILrun/endive/runtime/Memory;Lrun/endive/runtime/Instance;)I
    I2L
    LSTORE 4
    ICONST_1
    NEWARRAY T_LONG
    DUP
    ICONST_0
    LLOAD 4
    LASTORE
    ARETURN

  public static func_3(ILrun/endive/runtime/Memory;Lrun/endive/runtime/Instance;)I
    ILOAD 0
    ICONST_4
    IADD
    INVOKESTATIC run/endive/$gen/CompiledMachineShaded.checkInterruption ()V
    ALOAD 1
    ALOAD 2
    INVOKESTATIC run/endive/$gen/CompiledMachineFuncGroup_0.func_2 (ILrun/endive/runtime/Memory;Lrun/endive/runtime/Instance;)I
    IRETURN

  public static call_3(Lrun/endive/runtime/Instance;Lrun/endive/runtime/Memory;[J[Ljava/lang/Object;)[J
    ALOAD 2
    ICONST_0
    LALOAD
    L2I
    ALOAD 1
    ALOAD 0
    INVOKESTATIC run/endive/$gen/CompiledMachineFuncGroup_0.func_3 (ILrun/endive/runtime/Memory;Lrun/endive/runtime/Instance;)I
    I2L
    LSTORE 4
    ICONST_1
    NEWARRAY T_LONG
    DUP
    ICONST_0
    LLOAD 4
    LASTORE
    ARETURN

  public static func_4(ILrun/endive/runtime/Memory;Lrun/endive/runtime/Instance;)I
    ILOAD 0
    ICONST_5
    IADD
    INVOKESTATIC run/endive/$gen/CompiledMachineShaded.checkInterruption ()V
    ALOAD 1
    ALOAD 2
    INVOKESTATIC run/endive/$gen/CompiledMachineFuncGroup_0.func_3 (ILrun/endive/runtime/Memory;Lrun/endive/runtime/Instance;)I
    IRETURN

  public static call_4(Lrun/endive/runtime/Instance;Lrun/endive/runtime/Memory;[J[Ljava/lang/Object;)[J
    ALOAD 2
    ICONST_0
    LALOAD
    L2I
    ALOAD 1
    ALOAD 0
    INVOKESTATIC run/endive/$gen/CompiledMachineFuncGroup_0.func_4 (ILrun/endive/runtime/Memory;Lrun/endive/runtime/Instance;)I
    I2L
    LSTORE 4
    ICONST_1
    NEWARRAY T_LONG
    DUP
    ICONST_0
    LLOAD 4
    LASTORE
    ARETURN
}

final class run/endive/$gen/CompiledMachineFuncGroup_1 {

  public static func_5(ILrun/endive/runtime/Memory;Lrun/endive/runtime/Instance;)I
    ILOAD 0
    BIPUSH 6
    IADD
    INVOKESTATIC run/endive/$gen/CompiledMachineShaded.checkInterruption ()V
    ALOAD 1
    ALOAD 2
    INVOKESTATIC run/endive/$gen/CompiledMachineFuncGroup_0.func_4 (ILrun/endive/runtime/Memory;Lrun/endive/runtime/Instance;)I
    IRETURN

  public static call_5(Lrun/endive/runtime/Instance;Lrun/endive/runtime/Memory;[J[Ljava/lang/Object;)[J
    ALOAD 2
    ICONST_0
    LALOAD
    L2I
    ALOAD 1
    ALOAD 0
    INVOKESTATIC run/endive/$gen/CompiledMachineFuncGroup_1.func_5 (ILrun/endive/runtime/Memory;Lrun/endive/runtime/Instance;)I
    I2L
    LSTORE 4
    ICONST_1
    NEWARRAY T_LONG
    DUP
    ICONST_0
    LLOAD 4
    LASTORE
    ARETURN

  public static func_6(ILrun/endive/runtime/Memory;Lrun/endive/runtime/Instance;)I
    ILOAD 0
    BIPUSH 7
    IADD
    INVOKESTATIC run/endive/$gen/CompiledMachineShaded.checkInterruption ()V
    ALOAD 1
    ALOAD 2
    INVOKESTATIC run/endive/$gen/CompiledMachineFuncGroup_1.func_5 (ILrun/endive/runtime/Memory;Lrun/endive/runtime/Instance;)I
    IRETURN

  public static call_6(Lrun/endive/runtime/Instance;Lrun/endive/runtime/Memory;[J[Ljava/lang/Object;)[J
    ALOAD 2
    ICONST_0
    LALOAD
    L2I
    ALOAD 1
    ALOAD 0
    INVOKESTATIC run/endive/$gen/CompiledMachineFuncGroup_1.func_6 (ILrun/endive/runtime/Memory;Lrun/endive/runtime/Instance;)I
    I2L
    LSTORE 4
    ICONST_1
    NEWARRAY T_LONG
    DUP
    ICONST_0
    LLOAD 4
    LASTORE
    ARETURN

  public static func_7(ILrun/endive/runtime/Memory;Lrun/endive/runtime/Instance;)I
    ILOAD 0
    BIPUSH 8
    IADD
    INVOKESTATIC run/endive/$gen/CompiledMachineShaded.checkInterruption ()V
    ALOAD 1
    ALOAD 2
    INVOKESTATIC run/endive/$gen/CompiledMachineFuncGroup_1.func_6 (ILrun/endive/runtime/Memory;Lrun/endive/runtime/Instance;)I
    IRETURN

  public static call_7(Lrun/endive/runtime/Instance;Lrun/endive/runtime/Memory;[J[Ljava/lang/Object;)[J
    ALOAD 2
    ICONST_0
    LALOAD
    L2I
    ALOAD 1
    ALOAD 0
    INVOKESTATIC run/endive/$gen/CompiledMachineFuncGroup_1.func_7 (ILrun/endive/runtime/Memory;Lrun/endive/runtime/Instance;)I
    I2L
    LSTORE 4
    ICONST_1
    NEWARRAY T_LONG
    DUP
    ICONST_0
    LLOAD 4
    LASTORE
    ARETURN

  public static func_8(ILrun/endive/runtime/Memory;Lrun/endive/runtime/Instance;)I
    ILOAD 0
    BIPUSH 9
    IADD
    INVOKESTATIC run/endive/$gen/CompiledMachineShaded.checkInterruption ()V
    ALOAD 1
    ALOAD 2
    INVOKESTATIC run/endive/$gen/CompiledMachineFuncGroup_1.func_7 (ILrun/endive/runtime/Memory;Lrun/endive/runtime/Instance;)I
    IRETURN

  public static call_8(Lrun/endive/runtime/Instance;Lrun/endive/runtime/Memory;[J[Ljava/lang/Object;)[J
    ALOAD 2
    ICONST_0
    LALOAD
    L2I
    ALOAD 1
    ALOAD 0
    INVOKESTATIC run/endive/$gen/CompiledMachineFuncGroup_1.func_8 (ILrun/endive/runtime/Memory;Lrun/endive/runtime/Instance;)I
    I2L
    LSTORE 4
    ICONST_1
    NEWARRAY T_LONG
    DUP
    ICONST_0
    LLOAD 4
    LASTORE
    ARETURN

  public static func_9(ILrun/endive/runtime/Memory;Lrun/endive/runtime/Instance;)I
    ILOAD 0
    BIPUSH 10
    IADD
    INVOKESTATIC run/endive/$gen/CompiledMachineShaded.checkInterruption ()V
    ALOAD 1
    ALOAD 2
    INVOKESTATIC run/endive/$gen/CompiledMachineFuncGroup_1.func_8 (ILrun/endive/runtime/Memory;Lrun/endive/runtime/Instance;)I
    IRETURN

  public static call_9(Lrun/endive/runtime/Instance;Lrun/endive/runtime/Memory;[J[Ljava/lang/Object;)[J
    ALOAD 2
    ICONST_0
    LALOAD
    L2I
    ALOAD 1
    ALOAD 0
    INVOKESTATIC run/endive/$gen/CompiledMachineFuncGroup_1.func_9 (ILrun/endive/runtime/Memory;Lrun/endive/runtime/Instance;)I
    I2L
    LSTORE 4
    ICONST_1
    NEWARRAY T_LONG
    DUP
    ICONST_0
    LLOAD 4
    LASTORE
    ARETURN
}

final class run/endive/$gen/CompiledMachineMachineCall {

  public <init>()V
    ALOAD 0
    INVOKESPECIAL java/lang/Object.<init> ()V
    RETURN

  public static call(Lrun/endive/runtime/Instance;Lrun/endive/runtime/Memory;I[J[Ljava/lang/Object;)[J
    ALOAD 0
    ALOAD 1
    ALOAD 3
    ALOAD 4
    ILOAD 2
    TABLESWITCH
      0: L0
      1: L1
      2: L2
      3: L3
      4: L4
      5: L5
      6: L6
      7: L7
      8: L8
      9: L9
      default: L10
   L0
    INVOKESTATIC run/endive/$gen/CompiledMachineFuncGroup_0.call_0 (Lrun/endive/runtime/Instance;Lrun/endive/runtime/Memory;[J[Ljava/lang/Object;)[J
    ARETURN
   L1
    INVOKESTATIC run/endive/$gen/CompiledMachineFuncGroup_0.call_1 (Lrun/endive/runtime/Instance;Lrun/endive/runtime/Memory;[J[Ljava/lang/Object;)[J
    ARETURN
   L2
    INVOKESTATIC run/endive/$gen/CompiledMachineFuncGroup_0.call_2 (Lrun/endive/runtime/Instance;Lrun/endive/runtime/Memory;[J[Ljava/lang/Object;)[J
    ARETURN
   L3
    INVOKESTATIC run/endive/$gen/CompiledMachineFuncGroup_0.call_3 (Lrun/endive/runtime/Instance;Lrun/endive/runtime/Memory;[J[Ljava/lang/Object;)[J
    ARETURN
   L4
    INVOKESTATIC run/endive/$gen/CompiledMachineFuncGroup_0.call_4 (Lrun/endive/runtime/Instance;Lrun/endive/runtime/Memory;[J[Ljava/lang/Object;)[J
    ARETURN
   L5
    INVOKESTATIC run/endive/$gen/CompiledMachineFuncGroup_1.call_5 (Lrun/endive/runtime/Instance;Lrun/endive/runtime/Memory;[J[Ljava/lang/Object;)[J
    ARETURN
   L6
    INVOKESTATIC run/endive/$gen/CompiledMachineFuncGroup_1.call_6 (Lrun/endive/runtime/Instance;Lrun/endive/runtime/Memory;[J[Ljava/lang/Object;)[J
    ARETURN
   L7
    INVOKESTATIC run/endive/$gen/CompiledMachineFuncGroup_1.call_7 (Lrun/endive/runtime/Instance;Lrun/endive/runtime/Memory;[J[Ljava/lang/Object;)[J
    ARETURN
   L8
    INVOKESTATIC run/endive/$gen/CompiledMachineFuncGroup_1.call_8 (Lrun/endive/runtime/Instance;Lrun/endive/runtime/Memory;[J[Ljava/lang/Object;)[J
    ARETURN
   L9
    INVOKESTATIC run/endive/$gen/CompiledMachineFuncGroup_1.call_9 (Lrun/endive/runtime/Instance;Lrun/endive/runtime/Memory;[J[Ljava/lang/Object;)[J
    ARETURN
   L10
    ILOAD 2
    INVOKESTATIC run/endive/$gen/CompiledMachineShaded.throwUnknownFunction (I)Ljava/lang/RuntimeException;
    ATHROW
}
